{
  "generated_at": "2026-02-16T05:59:00",
  "lookback_days": 7,
  "saturation_threshold": 0.9,
  "rankings": {
    "cars": [
      {
        "name": "Gaumont OUEST",
        "mean_occ": 0.98,
        "max_occ": 0.98,
        "sat_pct": 1.0,
        "n_points": 134
      },
      {
        "name": "Arc de Triomphe",
        "mean_occ": 0.7273,
        "max_occ": 0.9114,
        "sat_pct": 0.0224,
        "n_points": 134
      },
      {
        "name": "Gaumont-Circe",
        "mean_occ": 0.602,
        "max_occ": 0.602,
        "sat_pct": 0.0,
        "n_points": 134
      },
      {
        "name": "Gambetta",
        "mean_occ": 0.6018,
        "max_occ": 0.7743,
        "sat_pct": 0.0,
        "n_points": 134
      },
      {
        "name": "Charles de Gaulle",
        "mean_occ": 0.5447,
        "max_occ": 0.8731,
        "sat_pct": 0.0,
        "n_points": 134
      },
      {
        "name": "Euromedecine",
        "mean_occ": 0.5378,
        "max_occ": 0.9414,
        "sat_pct": 0.0149,
        "n_points": 134
      },
      {
        "name": "Mosson",
        "mean_occ": 0.5262,
        "max_occ": 0.997,
        "sat_pct": 0.1194,
        "n_points": 134
      },
      {
        "name": "Comedie",
        "mean_occ": 0.5258,
        "max_occ": 0.9655,
        "sat_pct": 0.0672,
        "n_points": 134
      },
      {
        "name": "Gare",
        "mean_occ": 0.5199,
        "max_occ": 0.7988,
        "sat_pct": 0.0,
        "n_points": 134
      },
      {
        "name": "Occitanie",
        "mean_occ": 0.4956,
        "max_occ": 0.9805,
        "sat_pct": 0.0746,
        "n_points": 134
      },
      {
        "name": "Vicarello",
        "mean_occ": 0.4938,
        "max_occ": 0.8906,
        "sat_pct": 0.0,
        "n_points": 134
      },
      {
        "name": "Corum",
        "mean_occ": 0.4891,
        "max_occ": 0.9708,
        "sat_pct": 0.0299,
        "n_points": 134
      },
      {
        "name": "Polygone",
        "mean_occ": 0.4699,
        "max_occ": 0.4699,
        "sat_pct": 0.0,
        "n_points": 134
      },
      {
        "name": "Antigone",
        "mean_occ": 0.4053,
        "max_occ": 0.5105,
        "sat_pct": 0.0,
        "n_points": 134
      },
      {
        "name": "Triangle",
        "mean_occ": 0.3687,
        "max_occ": 0.3687,
        "sat_pct": 0.0,
        "n_points": 134
      },
      {
        "name": "Sablassou",
        "mean_occ": 0.3673,
        "max_occ": 0.7678,
        "sat_pct": 0.0,
        "n_points": 134
      },
      {
        "name": "Sabines",
        "mean_occ": 0.3416,
        "max_occ": 0.8842,
        "sat_pct": 0.0,
        "n_points": 134
      },
      {
        "name": "Gaumont EST",
        "mean_occ": 0.3211,
        "max_occ": 0.3211,
        "sat_pct": 0.0,
        "n_points": 134
      },
      {
        "name": "Pitot",
        "mean_occ": 0.3169,
        "max_occ": 0.3169,
        "sat_pct": 0.0,
        "n_points": 134
      },
      {
        "name": "Foch",
        "mean_occ": 0.2795,
        "max_occ": 0.5968,
        "sat_pct": 0.0,
        "n_points": 134
      },
      {
        "name": "Europa",
        "mean_occ": 0.2789,
        "max_occ": 0.6447,
        "sat_pct": 0.0,
        "n_points": 134
      },
      {
        "name": "Saint Jean Le Sec",
        "mean_occ": 0.2702,
        "max_occ": 0.4491,
        "sat_pct": 0.0,
        "n_points": 134
      },
      {
        "name": "Circe",
        "mean_occ": 0.1872,
        "max_occ": 0.4942,
        "sat_pct": 0.0,
        "n_points": 134
      },
      {
        "name": "Garcia Lorca",
        "mean_occ": 0.0744,
        "max_occ": 0.2825,
        "sat_pct": 0.0,
        "n_points": 134
      }
    ],
    "bikes": [
      {
        "name": "Antigone centre",
        "mean_occ": 0.7593,
        "max_occ": 1.0,
        "sat_pct": 0.2985,
        "n_points": 134
      },
      {
        "name": "Jardin de la Lironde",
        "mean_occ": 0.7388,
        "max_occ": 1.0,
        "sat_pct": 0.0448,
        "n_points": 134
      },
      {
        "name": "Hôtel du Département",
        "mean_occ": 0.7239,
        "max_occ": 0.875,
        "sat_pct": 0.0,
        "n_points": 134
      },
      {
        "name": "Cité Mion",
        "mean_occ": 0.7006,
        "max_occ": 1.0,
        "sat_pct": 0.0373,
        "n_points": 134
      },
      {
        "name": "Sud De France",
        "mean_occ": 0.6884,
        "max_occ": 1.0,
        "sat_pct": 0.0821,
        "n_points": 134
      },
      {
        "name": "Hôtel de Ville",
        "mean_occ": 0.6842,
        "max_occ": 1.0,
        "sat_pct": 0.0299,
        "n_points": 134
      },
      {
        "name": "Port Marianne",
        "mean_occ": 0.6819,
        "max_occ": 1.0,
        "sat_pct": 0.1418,
        "n_points": 134
      },
      {
        "name": "Providence - Ovalie",
        "mean_occ": 0.6679,
        "max_occ": 0.875,
        "sat_pct": 0.0,
        "n_points": 134
      },
      {
        "name": "Nouveau Saint-Roch",
        "mean_occ": 0.6576,
        "max_occ": 1.0,
        "sat_pct": 0.0448,
        "n_points": 134
      },
      {
        "name": "Garcia Lorca",
        "mean_occ": 0.6567,
        "max_occ": 0.875,
        "sat_pct": 0.0,
        "n_points": 134
      },
      {
        "name": "Richter",
        "mean_occ": 0.6432,
        "max_occ": 0.875,
        "sat_pct": 0.0,
        "n_points": 134
      },
      {
        "name": "Celleneuve",
        "mean_occ": 0.6399,
        "max_occ": 0.875,
        "sat_pct": 0.0,
        "n_points": 134
      },
      {
        "name": "Aiguelongue",
        "mean_occ": 0.6185,
        "max_occ": 0.875,
        "sat_pct": 0.0,
        "n_points": 134
      },
      {
        "name": "Jeu de Mail des Abbés",
        "mean_occ": 0.5625,
        "max_occ": 1.0,
        "sat_pct": 0.0896,
        "n_points": 134
      },
      {
        "name": "Pérols Etang de l Or",
        "mean_occ": 0.5537,
        "max_occ": 0.8529,
        "sat_pct": 0.0,
        "n_points": 134
      },
      {
        "name": "Occitanie",
        "mean_occ": 0.5487,
        "max_occ": 0.8125,
        "sat_pct": 0.0,
        "n_points": 134
      },
      {
        "name": "Renouvier",
        "mean_occ": 0.5159,
        "max_occ": 0.75,
        "sat_pct": 0.0,
        "n_points": 134
      },
      {
        "name": "Observatoire",
        "mean_occ": 0.5075,
        "max_occ": 1.0,
        "sat_pct": 0.0149,
        "n_points": 134
      },
      {
        "name": "Boutonnet",
        "mean_occ": 0.5044,
        "max_occ": 1.0,
        "sat_pct": 0.0299,
        "n_points": 134
      },
      {
        "name": "Voltaire",
        "mean_occ": 0.4711,
        "max_occ": 0.875,
        "sat_pct": 0.0,
        "n_points": 134
      },
      {
        "name": "Emile Combes",
        "mean_occ": 0.4636,
        "max_occ": 1.0,
        "sat_pct": 0.1269,
        "n_points": 134
      },
      {
        "name": "Nombre d Or",
        "mean_occ": 0.4566,
        "max_occ": 0.6875,
        "sat_pct": 0.0,
        "n_points": 134
      },
      {
        "name": "Médiathèque Emile Zola",
        "mean_occ": 0.4557,
        "max_occ": 0.75,
        "sat_pct": 0.0,
        "n_points": 134
      },
      {
        "name": "Prés d Arènes",
        "mean_occ": 0.4506,
        "max_occ": 1.0,
        "sat_pct": 0.097,
        "n_points": 134
      },
      {
        "name": "Place Viala",
        "mean_occ": 0.444,
        "max_occ": 1.0,
        "sat_pct": 0.0299,
        "n_points": 134
      },
      {
        "name": "Marie Caizergues",
        "mean_occ": 0.4328,
        "max_occ": 0.75,
        "sat_pct": 0.0,
        "n_points": 134
      },
      {
        "name": "Père Soulas",
        "mean_occ": 0.4086,
        "max_occ": 0.75,
        "sat_pct": 0.0,
        "n_points": 134
      },
      {
        "name": "Albert 1er - Cathédrale",
        "mean_occ": 0.4042,
        "max_occ": 0.5833,
        "sat_pct": 0.0,
        "n_points": 134
      },
      {
        "name": "FacdesSciences",
        "mean_occ": 0.394,
        "max_occ": 0.75,
        "sat_pct": 0.0,
        "n_points": 134
      },
      {
        "name": "Saint-Guilhem - Courreau",
        "mean_occ": 0.3927,
        "max_occ": 0.875,
        "sat_pct": 0.0,
        "n_points": 134
      },
      {
        "name": "Foch",
        "mean_occ": 0.3909,
        "max_occ": 0.75,
        "sat_pct": 0.0,
        "n_points": 134
      },
      {
        "name": "Les Aubes",
        "mean_occ": 0.3834,
        "max_occ": 0.75,
        "sat_pct": 0.0,
        "n_points": 134
      },
      {
        "name": "Beaux-Arts",
        "mean_occ": 0.3731,
        "max_occ": 0.5625,
        "sat_pct": 0.0,
        "n_points": 134
      },
      {
        "name": "Jean de Beins",
        "mean_occ": 0.3629,
        "max_occ": 0.4375,
        "sat_pct": 0.0,
        "n_points": 134
      },
      {
        "name": "Rondelet",
        "mean_occ": 0.3605,
        "max_occ": 0.5625,
        "sat_pct": 0.0,
        "n_points": 134
      },
      {
        "name": "Gambetta",
        "mean_occ": 0.3601,
        "max_occ": 0.625,
        "sat_pct": 0.0,
        "n_points": 134
      },
      {
        "name": "Charles Flahault",
        "mean_occ": 0.3526,
        "max_occ": 0.625,
        "sat_pct": 0.0,
        "n_points": 134
      },
      {
        "name": "Pont de Lattes - Gare Saint-Roch",
        "mean_occ": 0.347,
        "max_occ": 0.5833,
        "sat_pct": 0.0,
        "n_points": 134
      },
      {
        "name": "Rue Jules Ferry - Gare Saint-Roch",
        "mean_occ": 0.3439,
        "max_occ": 0.6667,
        "sat_pct": 0.0,
        "n_points": 134
      },
      {
        "name": "Malbosc",
        "mean_occ": 0.3368,
        "max_occ": 0.625,
        "sat_pct": 0.0,
        "n_points": 134
      },
      {
        "name": "Plan Cabanes",
        "mean_occ": 0.3327,
        "max_occ": 0.5833,
        "sat_pct": 0.0,
        "n_points": 134
      },
      {
        "name": "Comédie",
        "mean_occ": 0.3284,
        "max_occ": 0.95,
        "sat_pct": 0.0299,
        "n_points": 134
      },
      {
        "name": "Tonnelles",
        "mean_occ": 0.3153,
        "max_occ": 0.5,
        "sat_pct": 0.0,
        "n_points": 134
      },
      {
        "name": "Fac de Lettres",
        "mean_occ": 0.3047,
        "max_occ": 1.0,
        "sat_pct": 0.0299,
        "n_points": 134
      },
      {
        "name": "Place Albert 1er - St Charles",
        "mean_occ": 0.2875,
        "max_occ": 0.4444,
        "sat_pct": 0.0,
        "n_points": 134
      },
      {
        "name": "Vert Bois",
        "mean_occ": 0.2603,
        "max_occ": 0.5625,
        "sat_pct": 0.0,
        "n_points": 134
      },
      {
        "name": "Corum",
        "mean_occ": 0.2581,
        "max_occ": 0.6667,
        "sat_pct": 0.0,
        "n_points": 134
      },
      {
        "name": "Les Arceaux",
        "mean_occ": 0.2547,
        "max_occ": 0.375,
        "sat_pct": 0.0,
        "n_points": 134
      },
      {
        "name": "Sabines",
        "mean_occ": 0.2481,
        "max_occ": 0.5,
        "sat_pct": 0.0,
        "n_points": 134
      },
      {
        "name": "Parvis Jules Ferry - Gare Saint-Roch",
        "mean_occ": 0.2463,
        "max_occ": 0.375,
        "sat_pct": 0.0,
        "n_points": 134
      },
      {
        "name": "Louis Blanc",
        "mean_occ": 0.243,
        "max_occ": 0.625,
        "sat_pct": 0.0,
        "n_points": 134
      },
      {
        "name": "Euromédecine",
        "mean_occ": 0.2397,
        "max_occ": 0.5,
        "sat_pct": 0.0,
        "n_points": 134
      },
      {
        "name": "Comedie Baudin",
        "mean_occ": 0.0,
        "max_occ": 0.0,
        "sat_pct": 0.0,
        "n_points": 134
      },
      {
        "name": "Deux Ponts - Gare Saint-Roch",
        "mean_occ": 0.0,
        "max_occ": 0.0,
        "sat_pct": 0.0,
        "n_points": 134
      },
      {
        "name": "Halles Castellane",
        "mean_occ": 0.0,
        "max_occ": 0.0,
        "sat_pct": 0.0,
        "n_points": 134
      },
      {
        "name": "Odysseum",
        "mean_occ": 0.0,
        "max_occ": 0.0,
        "sat_pct": 0.0,
        "n_points": 134
      },
      {
        "name": "Saint-Denis",
        "mean_occ": 0.0,
        "max_occ": 0.0,
        "sat_pct": 0.0,
        "n_points": 134
      }
    ]
  },
  "city_curves": {
    "cars": {
      "timestamps": [
        "2026-02-09T06:01:00",
        "2026-02-09T07:08:00",
        "2026-02-09T08:58:00",
        "2026-02-09T09:55:00",
        "2026-02-09T11:03:00",
        "2026-02-09T12:03:00",
        "2026-02-09T12:52:00",
        "2026-02-09T14:12:00",
        "2026-02-09T15:53:00",
        "2026-02-09T16:57:00",
        "2026-02-09T18:51:00",
        "2026-02-09T20:13:00",
        "2026-02-09T21:03:00",
        "2026-02-09T21:54:00",
        "2026-02-09T22:39:00",
        "2026-02-09T23:37:00",
        "2026-02-10T00:37:00",
        "2026-02-10T03:32:00",
        "2026-02-10T06:04:00",
        "2026-02-10T07:15:00",
        "2026-02-10T08:59:00",
        "2026-02-10T09:58:00",
        "2026-02-10T11:01:00",
        "2026-02-10T11:58:00",
        "2026-02-10T12:51:00",
        "2026-02-10T14:16:00",
        "2026-02-10T15:59:00",
        "2026-02-10T17:06:00",
        "2026-02-10T19:03:00",
        "2026-02-10T20:19:00",
        "2026-02-10T21:45:00",
        "2026-02-10T22:42:00",
        "2026-02-10T23:41:00",
        "2026-02-11T00:39:00",
        "2026-02-11T03:29:00",
        "2026-02-11T06:03:00",
        "2026-02-11T07:12:00",
        "2026-02-11T08:55:00",
        "2026-02-11T09:51:00",
        "2026-02-11T10:54:00",
        "2026-02-11T11:52:00",
        "2026-02-11T12:46:00",
        "2026-02-11T14:13:00",
        "2026-02-11T15:54:00",
        "2026-02-11T17:03:00",
        "2026-02-11T18:13:00",
        "2026-02-11T20:05:00",
        "2026-02-11T20:57:00",
        "2026-02-11T21:40:00",
        "2026-02-11T22:34:00",
        "2026-02-11T23:30:00",
        "2026-02-12T00:34:00",
        "2026-02-12T03:24:00",
        "2026-02-12T05:58:00",
        "2026-02-12T07:05:00",
        "2026-02-12T08:14:00",
        "2026-02-12T09:50:00",
        "2026-02-12T10:52:00",
        "2026-02-12T11:48:00",
        "2026-02-12T12:40:00",
        "2026-02-12T14:10:00",
        "2026-02-12T15:49:00",
        "2026-02-12T16:54:00",
        "2026-02-12T18:00:00",
        "2026-02-12T18:56:00",
        "2026-02-12T20:04:00",
        "2026-02-12T20:51:00",
        "2026-02-12T21:36:00",
        "2026-02-12T22:35:00",
        "2026-02-12T23:34:00",
        "2026-02-13T00:30:00",
        "2026-02-13T03:25:00",
        "2026-02-13T05:53:00",
        "2026-02-13T07:00:00",
        "2026-02-13T08:01:00",
        "2026-02-13T08:51:00",
        "2026-02-13T09:43:00",
        "2026-02-13T10:45:00",
        "2026-02-13T11:40:00",
        "2026-02-13T12:31:00",
        "2026-02-13T14:02:00",
        "2026-02-13T15:04:00",
        "2026-02-13T15:54:00",
        "2026-02-13T16:43:00",
        "2026-02-13T17:49:00",
        "2026-02-13T18:40:00",
        "2026-02-13T19:52:00",
        "2026-02-13T20:42:00",
        "2026-02-13T21:39:00",
        "2026-02-13T22:37:00",
        "2026-02-13T23:34:00",
        "2026-02-14T00:31:00",
        "2026-02-14T03:06:00",
        "2026-02-14T05:42:00",
        "2026-02-14T06:45:00",
        "2026-02-14T07:47:00",
        "2026-02-14T08:34:00",
        "2026-02-14T09:34:00",
        "2026-02-14T10:32:00",
        "2026-02-14T11:28:00",
        "2026-02-14T12:23:00",
        "2026-02-14T14:45:00",
        "2026-02-14T15:28:00",
        "2026-02-14T16:27:00",
        "2026-02-14T17:31:00",
        "2026-02-14T18:26:00",
        "2026-02-14T19:36:00",
        "2026-02-14T20:25:00",
        "2026-02-14T21:28:00",
        "2026-02-14T22:25:00",
        "2026-02-14T23:25:00",
        "2026-02-15T00:25:00",
        "2026-02-15T03:25:00",
        "2026-02-15T05:54:00",
        "2026-02-15T06:57:00",
        "2026-02-15T07:53:00",
        "2026-02-15T08:38:00",
        "2026-02-15T09:34:00",
        "2026-02-15T10:33:00",
        "2026-02-15T11:28:00",
        "2026-02-15T13:53:00",
        "2026-02-15T14:47:00",
        "2026-02-15T15:28:00",
        "2026-02-15T16:26:00",
        "2026-02-15T17:32:00",
        "2026-02-15T18:26:00",
        "2026-02-15T19:38:00",
        "2026-02-15T20:26:00",
        "2026-02-15T21:28:00",
        "2026-02-15T22:26:00",
        "2026-02-15T23:26:00",
        "2026-02-16T00:28:00",
        "2026-02-16T03:22:00",
        "2026-02-16T05:59:00"
      ],
      "avg_occ": [
        0.3334,
        0.3461,
        0.4591,
        0.5167,
        0.5535,
        0.5479,
        0.5517,
        0.5719,
        0.5623,
        0.5254,
        0.4195,
        0.3923,
        0.3854,
        0.3757,
        0.3697,
        0.3542,
        0.3473,
        0.3443,
        0.3511,
        0.3687,
        0.5078,
        0.5833,
        0.6047,
        0.6068,
        0.6095,
        0.6168,
        0.5797,
        0.5525,
        0.4437,
        0.4277,
        0.3995,
        0.3779,
        0.356,
        0.3469,
        0.3417,
        0.3464,
        0.3559,
        0.4738,
        0.5422,
        0.574,
        0.5789,
        0.5894,
        0.5888,
        0.5804,
        0.5489,
        0.4741,
        0.4242,
        0.4244,
        0.4136,
        0.3932,
        0.3673,
        0.355,
        0.348,
        0.3499,
        0.3619,
        0.4204,
        0.5688,
        0.5964,
        0.5745,
        0.5829,
        0.5871,
        0.5751,
        0.5439,
        0.4812,
        0.4394,
        0.4303,
        0.4367,
        0.4269,
        0.4059,
        0.3853,
        0.366,
        0.3548,
        0.3536,
        0.3612,
        0.3926,
        0.4643,
        0.5162,
        0.5543,
        0.5726,
        0.5788,
        0.5774,
        0.5743,
        0.5642,
        0.5391,
        0.4915,
        0.4544,
        0.4673,
        0.4925,
        0.4862,
        0.4589,
        0.4287,
        0.3975,
        0.3788,
        0.3753,
        0.3455,
        0.3632,
        0.378,
        0.4204,
        0.4743,
        0.5114,
        0.5293,
        0.5352,
        0.5335,
        0.5265,
        0.5049,
        0.4889,
        0.485,
        0.4917,
        0.4936,
        0.468,
        0.4171,
        0.3914,
        0.367,
        0.3625,
        0.3615,
        0.3527,
        0.3517,
        0.365,
        0.3752,
        0.3854,
        0.3648,
        0.3567,
        0.3491,
        0.3541,
        0.3493,
        0.356,
        0.3588,
        0.3488,
        0.3464,
        0.3379,
        0.3303,
        0.3244,
        0.3225,
        0.3278
      ]
    },
    "bikes": {
      "timestamps": [
        "2026-02-09T06:01:00",
        "2026-02-09T07:08:00",
        "2026-02-09T08:58:00",
        "2026-02-09T09:55:00",
        "2026-02-09T11:03:00",
        "2026-02-09T12:03:00",
        "2026-02-09T12:52:00",
        "2026-02-09T14:12:00",
        "2026-02-09T15:53:00",
        "2026-02-09T16:57:00",
        "2026-02-09T18:51:00",
        "2026-02-09T20:13:00",
        "2026-02-09T21:03:00",
        "2026-02-09T21:54:00",
        "2026-02-09T22:39:00",
        "2026-02-09T23:37:00",
        "2026-02-10T00:37:00",
        "2026-02-10T03:32:00",
        "2026-02-10T06:04:00",
        "2026-02-10T07:15:00",
        "2026-02-10T08:59:00",
        "2026-02-10T09:58:00",
        "2026-02-10T11:01:00",
        "2026-02-10T11:58:00",
        "2026-02-10T12:51:00",
        "2026-02-10T14:16:00",
        "2026-02-10T15:59:00",
        "2026-02-10T17:06:00",
        "2026-02-10T19:03:00",
        "2026-02-10T20:19:00",
        "2026-02-10T21:45:00",
        "2026-02-10T22:42:00",
        "2026-02-10T23:41:00",
        "2026-02-11T00:39:00",
        "2026-02-11T03:29:00",
        "2026-02-11T06:03:00",
        "2026-02-11T07:12:00",
        "2026-02-11T08:55:00",
        "2026-02-11T09:51:00",
        "2026-02-11T10:54:00",
        "2026-02-11T11:52:00",
        "2026-02-11T12:46:00",
        "2026-02-11T14:13:00",
        "2026-02-11T15:54:00",
        "2026-02-11T17:03:00",
        "2026-02-11T18:13:00",
        "2026-02-11T20:05:00",
        "2026-02-11T20:57:00",
        "2026-02-11T21:40:00",
        "2026-02-11T22:34:00",
        "2026-02-11T23:30:00",
        "2026-02-12T00:34:00",
        "2026-02-12T03:24:00",
        "2026-02-12T05:58:00",
        "2026-02-12T07:05:00",
        "2026-02-12T08:14:00",
        "2026-02-12T09:50:00",
        "2026-02-12T10:52:00",
        "2026-02-12T11:48:00",
        "2026-02-12T12:40:00",
        "2026-02-12T14:10:00",
        "2026-02-12T15:49:00",
        "2026-02-12T16:54:00",
        "2026-02-12T18:00:00",
        "2026-02-12T18:56:00",
        "2026-02-12T20:04:00",
        "2026-02-12T20:51:00",
        "2026-02-12T21:36:00",
        "2026-02-12T22:35:00",
        "2026-02-12T23:34:00",
        "2026-02-13T00:30:00",
        "2026-02-13T03:25:00",
        "2026-02-13T05:53:00",
        "2026-02-13T07:00:00",
        "2026-02-13T08:01:00",
        "2026-02-13T08:51:00",
        "2026-02-13T09:43:00",
        "2026-02-13T10:45:00",
        "2026-02-13T11:40:00",
        "2026-02-13T12:31:00",
        "2026-02-13T14:02:00",
        "2026-02-13T15:04:00",
        "2026-02-13T15:54:00",
        "2026-02-13T16:43:00",
        "2026-02-13T17:49:00",
        "2026-02-13T18:40:00",
        "2026-02-13T19:52:00",
        "2026-02-13T20:42:00",
        "2026-02-13T21:39:00",
        "2026-02-13T22:37:00",
        "2026-02-13T23:34:00",
        "2026-02-14T00:31:00",
        "2026-02-14T03:06:00",
        "2026-02-14T05:42:00",
        "2026-02-14T06:45:00",
        "2026-02-14T07:47:00",
        "2026-02-14T08:34:00",
        "2026-02-14T09:34:00",
        "2026-02-14T10:32:00",
        "2026-02-14T11:28:00",
        "2026-02-14T12:23:00",
        "2026-02-14T14:45:00",
        "2026-02-14T15:28:00",
        "2026-02-14T16:27:00",
        "2026-02-14T17:31:00",
        "2026-02-14T18:26:00",
        "2026-02-14T19:36:00",
        "2026-02-14T20:25:00",
        "2026-02-14T21:28:00",
        "2026-02-14T22:25:00",
        "2026-02-14T23:25:00",
        "2026-02-15T00:25:00",
        "2026-02-15T03:25:00",
        "2026-02-15T05:54:00",
        "2026-02-15T06:57:00",
        "2026-02-15T07:53:00",
        "2026-02-15T08:38:00",
        "2026-02-15T09:34:00",
        "2026-02-15T10:33:00",
        "2026-02-15T11:28:00",
        "2026-02-15T13:53:00",
        "2026-02-15T14:47:00",
        "2026-02-15T15:28:00",
        "2026-02-15T16:26:00",
        "2026-02-15T17:32:00",
        "2026-02-15T18:26:00",
        "2026-02-15T19:38:00",
        "2026-02-15T20:26:00",
        "2026-02-15T21:28:00",
        "2026-02-15T22:26:00",
        "2026-02-15T23:26:00",
        "2026-02-16T00:28:00",
        "2026-02-16T03:22:00",
        "2026-02-16T05:59:00"
      ],
      "avg_occ": [
        0.4071,
        0.4054,
        0.405,
        0.3908,
        0.3949,
        0.3919,
        0.3809,
        0.3806,
        0.3874,
        0.4017,
        0.4202,
        0.4222,
        0.4307,
        0.4252,
        0.4259,
        0.4271,
        0.4254,
        0.4314,
        0.4307,
        0.4307,
        0.4188,
        0.4247,
        0.4178,
        0.4194,
        0.4209,
        0.4185,
        0.4199,
        0.43,
        0.4275,
        0.4333,
        0.4253,
        0.4231,
        0.4275,
        0.4275,
        0.4248,
        0.4274,
        0.4263,
        0.4219,
        0.4184,
        0.4153,
        0.4127,
        0.4037,
        0.3972,
        0.4107,
        0.4167,
        0.4148,
        0.4223,
        0.4202,
        0.4173,
        0.4286,
        0.4301,
        0.4265,
        0.429,
        0.4323,
        0.4315,
        0.4178,
        0.4167,
        0.4104,
        0.4078,
        0.3994,
        0.4111,
        0.4265,
        0.4309,
        0.4275,
        0.4207,
        0.4347,
        0.429,
        0.43,
        0.4324,
        0.442,
        0.4471,
        0.438,
        0.4402,
        0.4383,
        0.4325,
        0.4332,
        0.4275,
        0.4213,
        0.4143,
        0.4146,
        0.4212,
        0.4318,
        0.4358,
        0.4342,
        0.4367,
        0.4426,
        0.4429,
        0.4422,
        0.4422,
        0.4422,
        0.44,
        0.4422,
        0.4416,
        0.4446,
        0.4468,
        0.4463,
        0.4463,
        0.4494,
        0.4385,
        0.4384,
        0.4319,
        0.4151,
        0.4054,
        0.4142,
        0.4192,
        0.4256,
        0.4298,
        0.4234,
        0.4214,
        0.4264,
        0.4329,
        0.4329,
        0.414,
        0.402,
        0.4004,
        0.4062,
        0.4051,
        0.4035,
        0.3929,
        0.3566,
        0.356,
        0.3596,
        0.3525,
        0.3599,
        0.3659,
        0.3658,
        0.3684,
        0.3688,
        0.3724,
        0.3775,
        0.3743,
        0.3789,
        0.3842,
        0.3806
      ]
    }
  }
}